CQHDimensionalPhenotyper/CQHDimensionalPhenotyper.py
CQHDimensionalPhenotyper/__init__.py
CQHDimensionalPhenotyper/words.py
CQHDimensionalPhenotyper-0.1.3.dist-info/METADATA
CQHDimensionalPhenotyper-0.1.3.dist-info/WHEEL
CQHDimensionalPhenotyper-0.1.3.dist-info/top_level.txt
CQHDimensionalPhenotyper-0.1.3.dist-info/RECORD
